lusid_workflows/__init__.py
lusid_workflows/__version__.py
lusid_workflows/api_client.py
lusid_workflows/configuration.py
lusid_workflows/exceptions.py
lusid_workflows/rest.py
lusid_workflows/api/__init__.py
lusid_workflows/api/workflows_api.py
lusid_workflows/models/__init__.py
lusid_workflows/models/execute_workflow_request.py
lusid_workflows/models/link.py
lusid_workflows/models/lusid_problem_details.py
lusid_workflows/models/lusid_validation_problem_details.py
lusid_workflows/models/resource_list_of_workflow.py
lusid_workflows/models/resource_list_of_workflow_instance.py
lusid_workflows/models/transit_workflow_request.py
lusid_workflows/models/workflow.py
lusid_workflows/models/workflow_activity_summary.py
lusid_workflows/models/workflow_instance.py
lusid_workflows/utilities/__init__.py
lusid_workflows/utilities/config_keys.json
lusid_workflows/utilities/config_keys.py
lusid_workflows_sdk_generated_preview-0.1.25.dist-info/METADATA
lusid_workflows_sdk_generated_preview-0.1.25.dist-info/WHEEL
lusid_workflows_sdk_generated_preview-0.1.25.dist-info/top_level.txt
lusid_workflows_sdk_generated_preview-0.1.25.dist-info/RECORD
